<?xml version="1.0" ?><boxes_info 数据时间="2021-07-09-14:22:57">
		<camera_position>B_left</camera_position>
		<boxes>
			
			
		<hole><hole_box0><x>4883</x><y>892</y><w>97</w><h>98</h></hole_box0><hole_box1><x>3303</x><y>3260</y><w>132</w><h>129</h></hole_box1><hole_box2><x>2585</x><y>2936</y><w>121</w><h>117</h></hole_box2><hole_box3><x>2312</x><y>2615</y><w>117</w><h>123</h></hole_box3><hole_box4><x>4361</x><y>325</y><w>101</w><h>100</h></hole_box4><hole_box5><x>4700</x><y>2718</y><w>104</w><h>123</h></hole_box5><hole_box6><x>4653</x><y>568</y><w>117</w><h>108</h></hole_box6><hole_box7><x>3994</x><y>151</y><w>118</w><h>114</h></hole_box7><hole_box8><x>2054</x><y>1371</y><w>148</w><h>121</h></hole_box8><hole_box9><x>4411</x><y>2999</y><w>116</w><h>100</h></hole_box9><hole_box10><x>2460</x><y>592</y><w>135</w><h>107</h></hole_box10></hole><target/></boxes>
		<imgs>
			
			
		<hole><hole_img0><x>58.5</x><y>49.5</y><r>13.4</r><s>8</s></hole_img0><hole_img1><x>66.5</x><y>66.5</y><r>25.7</r><s>41</s></hole_img1><hole_img2><x>63.5</x><y>55.5</y><r>25.2</r><s>26</s></hole_img2><hole_img3><x>58.5</x><y>65.5</y><r>19.1</r><s>40</s></hole_img3><hole_img4><x>51.5</x><y>47.5</y><r>16.9</r><s>17</s></hole_img4><hole_img5><x>55.5</x><y>61.5</y><r>22.3</r><s>37</s></hole_img5><hole_img6><x>61.5</x><y>51.5</y><r>22.9</r><s>19</s></hole_img6><hole_img7><x>59.5</x><y>59.5</y><r>25.7</r><s>21</s></hole_img7><hole_img8><x>82.5</x><y>47.5</y><r>28.2</r><s>45</s></hole_img8><hole_img9><x>60.5</x><y>47.5</y><r>17.4</r><s>17</s></hole_img9><hole_img10><x>80.5</x><y>51.5</y><r>29.2</r><s>39</s></hole_img10></hole><target><target_img0><x>47.5</x><y>27.5</y><r>26.6</r><s>28</s></target_img0><target_img1><x>45.5</x><y>34.5</y><r>25.7</r><s>22</s></target_img1><target_img2><x>45.5</x><y>33.5</y><r>22.7</r><s>17</s></target_img2><target_img3><x>40.5</x><y>33.5</y><r>25.7</r><s>40</s></target_img3></target></imgs>
	</boxes_info>