<?xml version="1.0" ?><poseCaculate_data 数据时间="2021-06-23-11:20:52"><type>2021-5-19-22:42:12</type><A_end><center><X>1034.5332249994935</X><Y>-6577.920483956526</Y><Z>971.3372902014507</Z></center><angle_point><X>1111.8914154691251</X><Y>-1140.525955413112</Y><Z>-3635.1661556991403</Z></angle_point></A_end><B_end><center><X>233.20029539682616</X><Y>63.3832445814244</Y><Z>1066.0960110484414</Z></center><angle_point><X>210.1580935160211</X><Y>-188.6389504269657</Y><Z>1290.5428995978816</Z></angle_point></B_end><Axis><X>-801.3329296026674</X><Y>6641.3037285379505</Y><X>594.7587208469906</X></Axis><Angle><degree>-139.72509580325456</degree></Angle></poseCaculate_data>